aimd_limiter/__init__.py
aimd_limiter/limiter.py
aimd_limiter/py.typed
aimd_limiter-0.1.0.dist-info/METADATA
aimd_limiter-0.1.0.dist-info/WHEEL
aimd_limiter-0.1.0.dist-info/licenses/LICENSE
aimd_limiter-0.1.0.dist-info/RECORD
