Metadata-Version: 2.4
Name: aimd-limiter
Version: 0.1.0
Summary: Asynchronous AIMD-based rate limiter
Project-URL: Homepage, https://github.com/mxcoras/aimd-limiter
Project-URL: Repository, https://github.com/mxcoras/aimd-limiter
Project-URL: Issues, https://github.com/mxcoras/aimd-limiter/issues
Author: AIMD Limiter Contributors
License: MIT
License-File: LICENSE
Keywords: aimd,asyncio,networking,rate-limiter
Classifier: Development Status :: 3 - Alpha
Classifier: Intended Audience :: Developers
Classifier: License :: OSI Approved :: MIT License
Classifier: Programming Language :: Python
Classifier: Programming Language :: Python :: 3
Classifier: Programming Language :: Python :: 3.10
Classifier: Programming Language :: Python :: 3.11
Classifier: Programming Language :: Python :: 3.12
Classifier: Programming Language :: Python :: 3.13
Classifier: Programming Language :: Python :: 3.14
Classifier: Topic :: Software Development :: Libraries
Classifier: Topic :: Utilities
Requires-Python: >=3.10
